{
    "key": "group_616c40c16e511",
    "title": "Page URL Settings",
    "fields": [
        {
            "key": "field_616c40d9022e3",
            "label": "URLs",
            "name": "page_url",
            "type": "group",
            "instructions": "",
            "required": 0,
            "conditional_logic": 0,
            "wrapper": {
                "width": "",
                "class": "",
                "id": ""
            },
            "layout": "block",
            "sub_fields": [
                {
                    "key": "field_616c4177022e5",
                    "label": "Sign In",
                    "name": "sign_in",
                    "type": "url",
                    "instructions": "",
                    "required": 0,
                    "conditional_logic": 0,
                    "wrapper": {
                        "width": "",
                        "class": "",
                        "id": ""
                    },
                    "default_value": "",
                    "placeholder": ""
                },
                {
                    "key": "field_616c4138022e4",
                    "label": "Commercial Properties",
                    "name": "commercial_properties",
                    "type": "url",
                    "instructions": "",
                    "required": 0,
                    "conditional_logic": 0,
                    "wrapper": {
                        "width": "",
                        "class": "",
                        "id": ""
                    },
                    "default_value": "",
                    "placeholder": ""
                },
                {
                    "key": "field_616c418f022e6",
                    "label": "Property Valuation",
                    "name": "property_valuation",
                    "type": "url",
                    "instructions": "",
                    "required": 0,
                    "conditional_logic": 0,
                    "wrapper": {
                        "width": "",
                        "class": "",
                        "id": ""
                    },
                    "default_value": "",
                    "placeholder": ""
                }
            ]
        }
    ],
    "location": [
        [
            {
                "param": "options_page",
                "operator": "==",
                "value": "acf-options-theme"
            }
        ]
    ],
    "menu_order": 0,
    "position": "normal",
    "style": "default",
    "label_placement": "top",
    "instruction_placement": "label",
    "hide_on_screen": "",
    "active": true,
    "description": "",
    "modified": 1634484771
}